eagle_cooler/__init__.py
eagle_cooler/callback.py
eagle_cooler/context.py
eagle_cooler/core.py
eagle_cooler/model.py
eagle_cooler/webapi.py
eagle_cooler-0.1.1.dist-info/WHEEL
eagle_cooler-0.1.1.dist-info/entry_points.txt
eagle_cooler-0.1.1.dist-info/METADATA
eagle_cooler-0.1.1.dist-info/RECORD
