Metadata-Version: 2.3
Name: eagle-cooler
Version: 0.1.1
Summary: Python library for bridging Eagle js environment
Author: ZackaryW
Author-email: ZackaryW <gitzackw@gmail.com>
Requires-Dist: requests>=2.25.0
Requires-Python: >=3.13
